elastica/__init__.py
elastica/_calculus.py
elastica/_contact_functions.py
elastica/_linalg.py
elastica/_rotations.py
elastica/_synchronize_periodic_boundary.py
elastica/boundary_conditions.py
elastica/callback_functions.py
elastica/contact_forces.py
elastica/contact_utils.py
elastica/dissipation.py
elastica/external_forces.py
elastica/interaction.py
elastica/joint.py
elastica/py.typed
elastica/restart.py
elastica/transformations.py
elastica/typing.py
elastica/utils.py
elastica/version.py
elastica/collision/AABBCollection.py
elastica/experimental/__init__.py
elastica/experimental/interaction.py
elastica/experimental/connection_contact_joint/generic_system_type_connection.py
elastica/experimental/connection_contact_joint/parallel_connection.py
elastica/experimental/timestepper/explicit_steppers.py
elastica/experimental/timestepper/memory.py
elastica/experimental/timestepper/protocol.py
elastica/memory_block/__init__.py
elastica/memory_block/memory_block_rigid_body.py
elastica/memory_block/memory_block_rod.py
elastica/memory_block/memory_block_rod_base.py
elastica/memory_block/protocol.py
elastica/memory_block/utils.py
elastica/modules/__init__.py
elastica/modules/base_system.py
elastica/modules/callbacks.py
elastica/modules/connections.py
elastica/modules/constraints.py
elastica/modules/contact.py
elastica/modules/damping.py
elastica/modules/forcing.py
elastica/modules/memory_block.py
elastica/modules/operator_group.py
elastica/modules/protocol.py
elastica/reset_functions_for_block_structure/__init__.py
elastica/reset_functions_for_block_structure/_reset_ghost_vector_or_scalar.py
elastica/rigidbody/__init__.py
elastica/rigidbody/cylinder.py
elastica/rigidbody/data_structures.py
elastica/rigidbody/protocol.py
elastica/rigidbody/rigid_body.py
elastica/rigidbody/sphere.py
elastica/rod/__init__.py
elastica/rod/cosserat_rod.py
elastica/rod/data_structures.py
elastica/rod/factory_function.py
elastica/rod/knot_theory.py
elastica/rod/protocol.py
elastica/rod/rod_base.py
pyelastica-0.3.3.post2.dist-info/METADATA
pyelastica-0.3.3.post2.dist-info/WHEEL
pyelastica-0.3.3.post2.dist-info/licenses/LICENSE
pyelastica-0.3.3.post2.dist-info/RECORD
