Metadata-Version: 2.4
Name: pyelastica
Version: 0.3.3.post2
Summary: Elastica is a software to simulate the dynamics of filaments that, at every cross-section, can undergo all six possible modes of deformation, allowing the filament to bend, twist, stretch and shear, while interacting with complex environments via muscular activity, surface contact, friction and hydrodynamics.
Author-email: GazzolaLab <armant2@illinois.edu>, Seung Hyun Kim <skim0119@gmail.com>
License-Expression: MIT
License-File: LICENSE
Classifier: Development Status :: 4 - Beta
Classifier: Intended Audience :: Education
Classifier: Intended Audience :: Science/Research
Classifier: License :: OSI Approved :: MIT License
Classifier: Programming Language :: Python
Classifier: Programming Language :: Python :: 3.10
Classifier: Programming Language :: Python :: 3.11
Classifier: Programming Language :: Python :: 3.12
Classifier: Programming Language :: Python :: 3.13
Classifier: Programming Language :: Python :: Implementation :: CPython
Requires-Python: >=3.10
Requires-Dist: cma
Requires-Dist: flake8
Requires-Dist: matplotlib
Requires-Dist: mypy
Requires-Dist: mypy-extensions
Requires-Dist: numba
Requires-Dist: numpy
Requires-Dist: scipy
Requires-Dist: tqdm
Provides-Extra: dev
Requires-Dist: autoflake; extra == 'dev'
Requires-Dist: black; extra == 'dev'
Requires-Dist: click; extra == 'dev'
Requires-Dist: codecov; extra == 'dev'
Requires-Dist: coverage; extra == 'dev'
Requires-Dist: pre-commit; extra == 'dev'
Requires-Dist: pytest; extra == 'dev'
Requires-Dist: pytest-cov; extra == 'dev'
Requires-Dist: pytest-html; extra == 'dev'
Requires-Dist: pytest-mock; extra == 'dev'
Requires-Dist: pytest-rng; extra == 'dev'
Provides-Extra: docs
Requires-Dist: docutils>=0.18; extra == 'docs'
Requires-Dist: myst-parser>=1.0; extra == 'docs'
Requires-Dist: numpydoc>=1.3.1; extra == 'docs'
Requires-Dist: readthedocs-sphinx-search<0.4.0,>=0.1.1; extra == 'docs'
Requires-Dist: sphinx-autodoc-typehints>=1.21; extra == 'docs'
Requires-Dist: sphinx-book-theme>=1.0; extra == 'docs'
Requires-Dist: sphinx>=6.1; extra == 'docs'
Requires-Dist: sphinxcontrib-mermaid>=0.9.2; extra == 'docs'
